[{"WATER_SYSTEM_NUMBER":"CA5301002","VIOLATION_NUMBER":"9301008","VIOLATION_TYPE_NAME":"MCL,  AVERAGE","ANALYTE_NAME":"ARSENIC","RESULT":"0.0271","RESULT_UOM":"MG/L","MCL_VALUE":" ","MCL_UOM":" ","VIOL_BEGIN_DATE":"2014-01-01T08:00:00.000Z","VIOL_END_DATE":"2014-03-31T07:00:00.000Z","ENF_ACTION_NUMBER":"901005","ENF_ACTION_ISSUE_DATE":"2009-02-24T08:00:00.000Z","ENF_ACTION_TYPE_ISSUED":"FORMAL ENFORCEMENT ACTION ISSUED"},{"WATER_SYSTEM_NUMBER":"CA5301002","VIOLATION_NUMBER":"9301007","VIOLATION_TYPE_NAME":"MCL,  AVERAGE","ANALYTE_NAME":"ARSENIC","RESULT":".0178","RESULT_UOM":"MG/L","MCL_VALUE":" ","MCL_UOM":" ","VIOL_BEGIN_DATE":"2013-10-01T07:00:00.000Z","VIOL_END_DATE":"2013-12-31T08:00:00.000Z","ENF_ACTION_NUMBER":"901005","ENF_ACTION_ISSUE_DATE":"2009-02-24T08:00:00.000Z","ENF_ACTION_TYPE_ISSUED":"FORMAL ENFORCEMENT ACTION ISSUED"},{"WATER_SYSTEM_NUMBER":"CA5301002","VIOLATION_NUMBER":"9301013","VIOLATION_TYPE_NAME":"MCL,  AVERAGE","ANALYTE_NAME":"ARSENIC","RESULT":"0.0278","RESULT_UOM":"MG/L","MCL_VALUE":" ","MCL_UOM":" ","VIOL_BEGIN_DATE":"2015-04-01T07:00:00.000Z","VIOL_END_DATE":"2015-06-30T07:00:00.000Z","ENF_ACTION_NUMBER":"901005","ENF_ACTION_ISSUE_DATE":"2009-02-24T08:00:00.000Z","ENF_ACTION_TYPE_ISSUED":"FORMAL ENFORCEMENT ACTION ISSUED"},{"WATER_SYSTEM_NUMBER":"CA5301002","VIOLATION_NUMBER":"9301003","VIOLATION_TYPE_NAME":"MCL,  AVERAGE","ANALYTE_NAME":"ARSENIC","RESULT":"0.0266","RESULT_UOM":"MG/L","MCL_VALUE":"0.010","MCL_UOM":"MG/L","VIOL_BEGIN_DATE":"2012-10-01T07:00:00.000Z","VIOL_END_DATE":"2012-12-31T08:00:00.000Z","ENF_ACTION_NUMBER":"901005","ENF_ACTION_ISSUE_DATE":"2009-02-24T08:00:00.000Z","ENF_ACTION_TYPE_ISSUED":"FORMAL ENFORCEMENT ACTION ISSUED"},{"WATER_SYSTEM_NUMBER":"CA5301002","VIOLATION_NUMBER":"9301012","VIOLATION_TYPE_NAME":"MCL,  AVERAGE","ANALYTE_NAME":"ARSENIC","RESULT":"0.023","RESULT_UOM":"MG/L","MCL_VALUE":" ","MCL_UOM":" ","VIOL_BEGIN_DATE":"2015-01-01T08:00:00.000Z","VIOL_END_DATE":"2015-03-31T07:00:00.000Z","ENF_ACTION_NUMBER":"901005","ENF_ACTION_ISSUE_DATE":"2009-02-24T08:00:00.000Z","ENF_ACTION_TYPE_ISSUED":"FORMAL ENFORCEMENT ACTION ISSUED"},{"WATER_SYSTEM_NUMBER":"CA5301002","VIOLATION_NUMBER":"1201021","VIOLATION_TYPE_NAME":"MCL,  AVERAGE","ANALYTE_NAME":"ARSENIC","RESULT":".02720000","RESULT_UOM":"MG/L","MCL_VALUE":"0.010","MCL_UOM":"MG/L","VIOL_BEGIN_DATE":"2012-07-01T07:00:00.000Z","VIOL_END_DATE":"2012-09-30T07:00:00.000Z","ENF_ACTION_NUMBER":"901005","ENF_ACTION_ISSUE_DATE":"2009-02-24T08:00:00.000Z","ENF_ACTION_TYPE_ISSUED":"FORMAL ENFORCEMENT ACTION ISSUED"},{"WATER_SYSTEM_NUMBER":"CA5301002","VIOLATION_NUMBER":"1201020","VIOLATION_TYPE_NAME":"MCL,  AVERAGE","ANALYTE_NAME":"ARSENIC","RESULT":".02710000","RESULT_UOM":"MG/L","MCL_VALUE":"0.010","MCL_UOM":"MG/L","VIOL_BEGIN_DATE":"2012-04-01T07:00:00.000Z","VIOL_END_DATE":"2012-06-30T07:00:00.000Z","ENF_ACTION_NUMBER":"901005","ENF_ACTION_ISSUE_DATE":"2009-02-24T08:00:00.000Z","ENF_ACTION_TYPE_ISSUED":"FORMAL ENFORCEMENT ACTION ISSUED"},{"WATER_SYSTEM_NUMBER":"CA5301002","VIOLATION_NUMBER":"1201016","VIOLATION_TYPE_NAME":"MCL,  AVERAGE","ANALYTE_NAME":"ARSENIC","RESULT":".02580000","RESULT_UOM":"MG/L","MCL_VALUE":"0.010","MCL_UOM":"MG/L","VIOL_BEGIN_DATE":"2012-01-01T08:00:00.000Z","VIOL_END_DATE":"2012-03-31T07:00:00.000Z","ENF_ACTION_NUMBER":"901005","ENF_ACTION_ISSUE_DATE":"2009-02-24T08:00:00.000Z","ENF_ACTION_TYPE_ISSUED":"FORMAL ENFORCEMENT ACTION ISSUED"},{"WATER_SYSTEM_NUMBER":"CA5301002","VIOLATION_NUMBER":"9301009","VIOLATION_TYPE_NAME":"MCL,  AVERAGE","ANALYTE_NAME":"ARSENIC","RESULT":".0194","RESULT_UOM":"MG/L","MCL_VALUE":" ","MCL_UOM":" ","VIOL_BEGIN_DATE":"2014-04-01T07:00:00.000Z","VIOL_END_DATE":"2014-06-30T07:00:00.000Z","ENF_ACTION_NUMBER":"901005","ENF_ACTION_ISSUE_DATE":"2009-02-24T08:00:00.000Z","ENF_ACTION_TYPE_ISSUED":"FORMAL ENFORCEMENT ACTION ISSUED"},{"WATER_SYSTEM_NUMBER":"CA5301002","VIOLATION_NUMBER":"9301010","VIOLATION_TYPE_NAME":"MCL,  AVERAGE","ANALYTE_NAME":"ARSENIC","RESULT":".0194","RESULT_UOM":"MG/L","MCL_VALUE":" ","MCL_UOM":" ","VIOL_BEGIN_DATE":"2014-07-01T07:00:00.000Z","VIOL_END_DATE":"2014-09-30T07:00:00.000Z","ENF_ACTION_NUMBER":"901005","ENF_ACTION_ISSUE_DATE":"2009-02-24T08:00:00.000Z","ENF_ACTION_TYPE_ISSUED":"FORMAL ENFORCEMENT ACTION ISSUED"},{"WATER_SYSTEM_NUMBER":"CA5301002","VIOLATION_NUMBER":"9301011","VIOLATION_TYPE_NAME":"MCL,  AVERAGE","ANALYTE_NAME":"ARSENIC","RESULT":"0.0204","RESULT_UOM":"MG/L","MCL_VALUE":" ","MCL_UOM":" ","VIOL_BEGIN_DATE":"2014-10-01T07:00:00.000Z","VIOL_END_DATE":"2014-12-31T08:00:00.000Z","ENF_ACTION_NUMBER":"901005","ENF_ACTION_ISSUE_DATE":"2009-02-24T08:00:00.000Z","ENF_ACTION_TYPE_ISSUED":"FORMAL ENFORCEMENT ACTION ISSUED"},{"WATER_SYSTEM_NUMBER":"CA5301002","VIOLATION_NUMBER":"9301004","VIOLATION_TYPE_NAME":"MCL,  AVERAGE","ANALYTE_NAME":"ARSENIC","RESULT":".0234","RESULT_UOM":"MG/L","MCL_VALUE":" ","MCL_UOM":" ","VIOL_BEGIN_DATE":"2013-01-01T08:00:00.000Z","VIOL_END_DATE":"2013-03-31T07:00:00.000Z","ENF_ACTION_NUMBER":"901005","ENF_ACTION_ISSUE_DATE":"2009-02-24T08:00:00.000Z","ENF_ACTION_TYPE_ISSUED":"FORMAL ENFORCEMENT ACTION ISSUED"},{"WATER_SYSTEM_NUMBER":"CA5301002","VIOLATION_NUMBER":"9301005","VIOLATION_TYPE_NAME":"MCL,  AVERAGE","ANALYTE_NAME":"ARSENIC","RESULT":"0.0195","RESULT_UOM":"MG/L","MCL_VALUE":" ","MCL_UOM":" ","VIOL_BEGIN_DATE":"2013-04-01T07:00:00.000Z","VIOL_END_DATE":"2013-06-30T07:00:00.000Z","ENF_ACTION_NUMBER":"901005","ENF_ACTION_ISSUE_DATE":"2009-02-24T08:00:00.000Z","ENF_ACTION_TYPE_ISSUED":"FORMAL ENFORCEMENT ACTION ISSUED"},{"WATER_SYSTEM_NUMBER":"CA5301002","VIOLATION_NUMBER":"9301006","VIOLATION_TYPE_NAME":"MCL,  AVERAGE","ANALYTE_NAME":"ARSENIC","RESULT":"0.0186","RESULT_UOM":"MG/L","MCL_VALUE":" ","MCL_UOM":" ","VIOL_BEGIN_DATE":"2013-07-01T07:00:00.000Z","VIOL_END_DATE":"2013-09-30T07:00:00.000Z","ENF_ACTION_NUMBER":"901005","ENF_ACTION_ISSUE_DATE":"2009-02-24T08:00:00.000Z","ENF_ACTION_TYPE_ISSUED":"FORMAL ENFORCEMENT ACTION ISSUED"},{"WATER_SYSTEM_NUMBER":"CA5301002","VIOLATION_NUMBER":"9301008","VIOLATION_TYPE_NAME":"MCL,  AVERAGE","ANALYTE_NAME":"ARSENIC","RESULT":"0.0271","RESULT_UOM":"MG/L","MCL_VALUE":" ","MCL_UOM":" ","VIOL_BEGIN_DATE":"2014-01-01T08:00:00.000Z","VIOL_END_DATE":"2014-03-31T07:00:00.000Z","ENF_ACTION_NUMBER":"9501004","ENF_ACTION_ISSUE_DATE":"2015-08-25T07:00:00.000Z","ENF_ACTION_TYPE_ISSUED":"RETURN TO COMPLIANCE"},{"WATER_SYSTEM_NUMBER":"CA5301002","VIOLATION_NUMBER":"9301007","VIOLATION_TYPE_NAME":"MCL,  AVERAGE","ANALYTE_NAME":"ARSENIC","RESULT":".0178","RESULT_UOM":"MG/L","MCL_VALUE":" ","MCL_UOM":" ","VIOL_BEGIN_DATE":"2013-10-01T07:00:00.000Z","VIOL_END_DATE":"2013-12-31T08:00:00.000Z","ENF_ACTION_NUMBER":"9501004","ENF_ACTION_ISSUE_DATE":"2015-08-25T07:00:00.000Z","ENF_ACTION_TYPE_ISSUED":"RETURN TO COMPLIANCE"},{"WATER_SYSTEM_NUMBER":"CA5301002","VIOLATION_NUMBER":"9301013","VIOLATION_TYPE_NAME":"MCL,  AVERAGE","ANALYTE_NAME":"ARSENIC","RESULT":"0.0278","RESULT_UOM":"MG/L","MCL_VALUE":" ","MCL_UOM":" ","VIOL_BEGIN_DATE":"2015-04-01T07:00:00.000Z","VIOL_END_DATE":"2015-06-30T07:00:00.000Z","ENF_ACTION_NUMBER":"9501004","ENF_ACTION_ISSUE_DATE":"2015-08-25T07:00:00.000Z","ENF_ACTION_TYPE_ISSUED":"RETURN TO COMPLIANCE"},{"WATER_SYSTEM_NUMBER":"CA5301002","VIOLATION_NUMBER":"9301003","VIOLATION_TYPE_NAME":"MCL,  AVERAGE","ANALYTE_NAME":"ARSENIC","RESULT":"0.0266","RESULT_UOM":"MG/L","MCL_VALUE":"0.010","MCL_UOM":"MG/L","VIOL_BEGIN_DATE":"2012-10-01T07:00:00.000Z","VIOL_END_DATE":"2012-12-31T08:00:00.000Z","ENF_ACTION_NUMBER":"9501004","ENF_ACTION_ISSUE_DATE":"2015-08-25T07:00:00.000Z","ENF_ACTION_TYPE_ISSUED":"RETURN TO COMPLIANCE"},{"WATER_SYSTEM_NUMBER":"CA5301002","VIOLATION_NUMBER":"9301012","VIOLATION_TYPE_NAME":"MCL,  AVERAGE","ANALYTE_NAME":"ARSENIC","RESULT":"0.023","RESULT_UOM":"MG/L","MCL_VALUE":" ","MCL_UOM":" ","VIOL_BEGIN_DATE":"2015-01-01T08:00:00.000Z","VIOL_END_DATE":"2015-03-31T07:00:00.000Z","ENF_ACTION_NUMBER":"9501004","ENF_ACTION_ISSUE_DATE":"2015-08-25T07:00:00.000Z","ENF_ACTION_TYPE_ISSUED":"RETURN TO COMPLIANCE"},{"WATER_SYSTEM_NUMBER":"CA5301002","VIOLATION_NUMBER":"1201021","VIOLATION_TYPE_NAME":"MCL,  AVERAGE","ANALYTE_NAME":"ARSENIC","RESULT":".02720000","RESULT_UOM":"MG/L","MCL_VALUE":"0.010","MCL_UOM":"MG/L","VIOL_BEGIN_DATE":"2012-07-01T07:00:00.000Z","VIOL_END_DATE":"2012-09-30T07:00:00.000Z","ENF_ACTION_NUMBER":"9501004","ENF_ACTION_ISSUE_DATE":"2015-08-25T07:00:00.000Z","ENF_ACTION_TYPE_ISSUED":"RETURN TO COMPLIANCE"},{"WATER_SYSTEM_NUMBER":"CA5301002","VIOLATION_NUMBER":"1201020","VIOLATION_TYPE_NAME":"MCL,  AVERAGE","ANALYTE_NAME":"ARSENIC","RESULT":".02710000","RESULT_UOM":"MG/L","MCL_VALUE":"0.010","MCL_UOM":"MG/L","VIOL_BEGIN_DATE":"2012-04-01T07:00:00.000Z","VIOL_END_DATE":"2012-06-30T07:00:00.000Z","ENF_ACTION_NUMBER":"9501004","ENF_ACTION_ISSUE_DATE":"2015-08-25T07:00:00.000Z","ENF_ACTION_TYPE_ISSUED":"RETURN TO COMPLIANCE"},{"WATER_SYSTEM_NUMBER":"CA5301002","VIOLATION_NUMBER":"1201016","VIOLATION_TYPE_NAME":"MCL,  AVERAGE","ANALYTE_NAME":"ARSENIC","RESULT":".02580000","RESULT_UOM":"MG/L","MCL_VALUE":"0.010","MCL_UOM":"MG/L","VIOL_BEGIN_DATE":"2012-01-01T08:00:00.000Z","VIOL_END_DATE":"2012-03-31T07:00:00.000Z","ENF_ACTION_NUMBER":"9501004","ENF_ACTION_ISSUE_DATE":"2015-08-25T07:00:00.000Z","ENF_ACTION_TYPE_ISSUED":"RETURN TO COMPLIANCE"},{"WATER_SYSTEM_NUMBER":"CA5301002","VIOLATION_NUMBER":"9301009","VIOLATION_TYPE_NAME":"MCL,  AVERAGE","ANALYTE_NAME":"ARSENIC","RESULT":".0194","RESULT_UOM":"MG/L","MCL_VALUE":" ","MCL_UOM":" ","VIOL_BEGIN_DATE":"2014-04-01T07:00:00.000Z","VIOL_END_DATE":"2014-06-30T07:00:00.000Z","ENF_ACTION_NUMBER":"9501004","ENF_ACTION_ISSUE_DATE":"2015-08-25T07:00:00.000Z","ENF_ACTION_TYPE_ISSUED":"RETURN TO COMPLIANCE"},{"WATER_SYSTEM_NUMBER":"CA5301002","VIOLATION_NUMBER":"9301010","VIOLATION_TYPE_NAME":"MCL,  AVERAGE","ANALYTE_NAME":"ARSENIC","RESULT":".0194","RESULT_UOM":"MG/L","MCL_VALUE":" ","MCL_UOM":" ","VIOL_BEGIN_DATE":"2014-07-01T07:00:00.000Z","VIOL_END_DATE":"2014-09-30T07:00:00.000Z","ENF_ACTION_NUMBER":"9501004","ENF_ACTION_ISSUE_DATE":"2015-08-25T07:00:00.000Z","ENF_ACTION_TYPE_ISSUED":"RETURN TO COMPLIANCE"},{"WATER_SYSTEM_NUMBER":"CA5301002","VIOLATION_NUMBER":"9301011","VIOLATION_TYPE_NAME":"MCL,  AVERAGE","ANALYTE_NAME":"ARSENIC","RESULT":"0.0204","RESULT_UOM":"MG/L","MCL_VALUE":" ","MCL_UOM":" ","VIOL_BEGIN_DATE":"2014-10-01T07:00:00.000Z","VIOL_END_DATE":"2014-12-31T08:00:00.000Z","ENF_ACTION_NUMBER":"9501004","ENF_ACTION_ISSUE_DATE":"2015-08-25T07:00:00.000Z","ENF_ACTION_TYPE_ISSUED":"RETURN TO COMPLIANCE"},{"WATER_SYSTEM_NUMBER":"CA5301002","VIOLATION_NUMBER":"9301004","VIOLATION_TYPE_NAME":"MCL,  AVERAGE","ANALYTE_NAME":"ARSENIC","RESULT":".0234","RESULT_UOM":"MG/L","MCL_VALUE":" ","MCL_UOM":" ","VIOL_BEGIN_DATE":"2013-01-01T08:00:00.000Z","VIOL_END_DATE":"2013-03-31T07:00:00.000Z","ENF_ACTION_NUMBER":"9501004","ENF_ACTION_ISSUE_DATE":"2015-08-25T07:00:00.000Z","ENF_ACTION_TYPE_ISSUED":"RETURN TO COMPLIANCE"},{"WATER_SYSTEM_NUMBER":"CA5301002","VIOLATION_NUMBER":"9301005","VIOLATION_TYPE_NAME":"MCL,  AVERAGE","ANALYTE_NAME":"ARSENIC","RESULT":"0.0195","RESULT_UOM":"MG/L","MCL_VALUE":" ","MCL_UOM":" ","VIOL_BEGIN_DATE":"2013-04-01T07:00:00.000Z","VIOL_END_DATE":"2013-06-30T07:00:00.000Z","ENF_ACTION_NUMBER":"9501004","ENF_ACTION_ISSUE_DATE":"2015-08-25T07:00:00.000Z","ENF_ACTION_TYPE_ISSUED":"RETURN TO COMPLIANCE"},{"WATER_SYSTEM_NUMBER":"CA5301002","VIOLATION_NUMBER":"9301006","VIOLATION_TYPE_NAME":"MCL,  AVERAGE","ANALYTE_NAME":"ARSENIC","RESULT":"0.0186","RESULT_UOM":"MG/L","MCL_VALUE":" ","MCL_UOM":" ","VIOL_BEGIN_DATE":"2013-07-01T07:00:00.000Z","VIOL_END_DATE":"2013-09-30T07:00:00.000Z","ENF_ACTION_NUMBER":"9501004","ENF_ACTION_ISSUE_DATE":"2015-08-25T07:00:00.000Z","ENF_ACTION_TYPE_ISSUED":"RETURN TO COMPLIANCE"}]