{"type":"Feature","properties":{"ObjectID":93081,"WATER_SYST":"CA1502154","WATER_SY_1":"LAKESIDE SCHOOL","REGULATING":"DISTRICT 12 - VISALIA","COUNTY":"KERN","POPULATION":"800","CLASSIFICA":"NON-TRANSIENT NON-COMMUNITY","CITY_1":"BAKERSFIELD","ZIPCODE":"93311","GIS_STATUS":"OUT-OF-COMPLIANCE","DEFAULT_ME":null,"Service_Co":1,"DETAILED_V":"https://www.waterboards.ca.gov/water_issues/programs/hr2w/docs/data/hr2w_web_data_active.xlsx"},"geometry":{"type":"Point","coordinates":[-119.11318275901783,35.315581159197684]}}