[{"WATER_SYSTEM_NUMBER":"CA1200544","VIOLATION_NUMBER":"9401004","VIOLATION_TYPE_NAME":"MONTHLY COMB FLTR EFFLUENT (IESWTR/LT1)","ANALYTE_NAME":"IESWTR","RESULT":" ","RESULT_UOM":" ","MCL_VALUE":" ","MCL_UOM":" ","VIOL_BEGIN_DATE":"2016-01-01T08:00:00.000Z","VIOL_END_DATE":"2016-03-31T07:00:00.000Z","ENF_ACTION_NUMBER":"1101029","ENF_ACTION_ISSUE_DATE":"2011-06-24T07:00:00.000Z","ENF_ACTION_TYPE_ISSUED":"FORMAL ENFORCEMENT ACTION ISSUED","WATER_SYSTEM_NAME":"REDCREST WATER WORKS","REGULATING_AGENCY":"DISTRICT 01 - KLAMATH","COUNTY":"HUMBOLDT","POPULATION":"100","CITY":"REDCREST","ZIPCODE":"95569"},{"WATER_SYSTEM_NUMBER":"CA1200544","VIOLATION_NUMBER":"9401007","VIOLATION_TYPE_NAME":"MONTHLY COMB FLTR EFFLUENT (IESWTR/LT1)","ANALYTE_NAME":"IESWTR","RESULT":" ","RESULT_UOM":" ","MCL_VALUE":" ","MCL_UOM":" ","VIOL_BEGIN_DATE":"2016-10-01T07:00:00.000Z","VIOL_END_DATE":"2016-12-31T08:00:00.000Z","ENF_ACTION_NUMBER":"1101029","ENF_ACTION_ISSUE_DATE":"2011-06-24T07:00:00.000Z","ENF_ACTION_TYPE_ISSUED":"FORMAL ENFORCEMENT ACTION ISSUED","WATER_SYSTEM_NAME":"REDCREST WATER WORKS","REGULATING_AGENCY":"DISTRICT 01 - KLAMATH","COUNTY":"HUMBOLDT","POPULATION":"100","CITY":"REDCREST","ZIPCODE":"95569"},{"WATER_SYSTEM_NUMBER":"CA1200544","VIOLATION_NUMBER":"9401006","VIOLATION_TYPE_NAME":"MONTHLY COMB FLTR EFFLUENT (IESWTR/LT1)","ANALYTE_NAME":"IESWTR","RESULT":" ","RESULT_UOM":" ","MCL_VALUE":" ","MCL_UOM":" ","VIOL_BEGIN_DATE":"2016-05-01T07:00:00.000Z","VIOL_END_DATE":"2016-05-31T07:00:00.000Z","ENF_ACTION_NUMBER":"1101029","ENF_ACTION_ISSUE_DATE":"2011-06-24T07:00:00.000Z","ENF_ACTION_TYPE_ISSUED":"FORMAL ENFORCEMENT ACTION ISSUED","WATER_SYSTEM_NAME":"REDCREST WATER WORKS","REGULATING_AGENCY":"DISTRICT 01 - KLAMATH","COUNTY":"HUMBOLDT","POPULATION":"100","CITY":"REDCREST","ZIPCODE":"95569"},{"WATER_SYSTEM_NUMBER":"CA1200544","VIOLATION_NUMBER":"9401005","VIOLATION_TYPE_NAME":"MONTHLY COMB FLTR EFFLUENT (IESWTR/LT1)","ANALYTE_NAME":"IESWTR","RESULT":" ","RESULT_UOM":" ","MCL_VALUE":" ","MCL_UOM":" ","VIOL_BEGIN_DATE":"2016-04-01T07:00:00.000Z","VIOL_END_DATE":"2016-04-30T07:00:00.000Z","ENF_ACTION_NUMBER":"1101029","ENF_ACTION_ISSUE_DATE":"2011-06-24T07:00:00.000Z","ENF_ACTION_TYPE_ISSUED":"FORMAL ENFORCEMENT ACTION ISSUED","WATER_SYSTEM_NAME":"REDCREST WATER WORKS","REGULATING_AGENCY":"DISTRICT 01 - KLAMATH","COUNTY":"HUMBOLDT","POPULATION":"100","CITY":"REDCREST","ZIPCODE":"95569"},{"WATER_SYSTEM_NUMBER":"CA1200544","VIOLATION_NUMBER":"9401004","VIOLATION_TYPE_NAME":"MONTHLY COMB FLTR EFFLUENT (IESWTR/LT1)","ANALYTE_NAME":"IESWTR","RESULT":" ","RESULT_UOM":" ","MCL_VALUE":" ","MCL_UOM":" ","VIOL_BEGIN_DATE":"2016-01-01T08:00:00.000Z","VIOL_END_DATE":"2016-03-31T07:00:00.000Z","ENF_ACTION_NUMBER":"9501008","ENF_ACTION_ISSUE_DATE":"2018-02-28T08:00:00.000Z","ENF_ACTION_TYPE_ISSUED":"RETURN TO COMPLIANCE","WATER_SYSTEM_NAME":"REDCREST WATER WORKS","REGULATING_AGENCY":"DISTRICT 01 - KLAMATH","COUNTY":"HUMBOLDT","POPULATION":"100","CITY":"REDCREST","ZIPCODE":"95569"},{"WATER_SYSTEM_NUMBER":"CA1200544","VIOLATION_NUMBER":"9401007","VIOLATION_TYPE_NAME":"MONTHLY COMB FLTR EFFLUENT (IESWTR/LT1)","ANALYTE_NAME":"IESWTR","RESULT":" ","RESULT_UOM":" ","MCL_VALUE":" ","MCL_UOM":" ","VIOL_BEGIN_DATE":"2016-10-01T07:00:00.000Z","VIOL_END_DATE":"2016-12-31T08:00:00.000Z","ENF_ACTION_NUMBER":"9501008","ENF_ACTION_ISSUE_DATE":"2018-02-28T08:00:00.000Z","ENF_ACTION_TYPE_ISSUED":"RETURN TO COMPLIANCE","WATER_SYSTEM_NAME":"REDCREST WATER WORKS","REGULATING_AGENCY":"DISTRICT 01 - KLAMATH","COUNTY":"HUMBOLDT","POPULATION":"100","CITY":"REDCREST","ZIPCODE":"95569"},{"WATER_SYSTEM_NUMBER":"CA1200544","VIOLATION_NUMBER":"9401006","VIOLATION_TYPE_NAME":"MONTHLY COMB FLTR EFFLUENT (IESWTR/LT1)","ANALYTE_NAME":"IESWTR","RESULT":" ","RESULT_UOM":" ","MCL_VALUE":" ","MCL_UOM":" ","VIOL_BEGIN_DATE":"2016-05-01T07:00:00.000Z","VIOL_END_DATE":"2016-05-31T07:00:00.000Z","ENF_ACTION_NUMBER":"9501008","ENF_ACTION_ISSUE_DATE":"2018-02-28T08:00:00.000Z","ENF_ACTION_TYPE_ISSUED":"RETURN TO COMPLIANCE","WATER_SYSTEM_NAME":"REDCREST WATER WORKS","REGULATING_AGENCY":"DISTRICT 01 - KLAMATH","COUNTY":"HUMBOLDT","POPULATION":"100","CITY":"REDCREST","ZIPCODE":"95569"},{"WATER_SYSTEM_NUMBER":"CA1200544","VIOLATION_NUMBER":"9401005","VIOLATION_TYPE_NAME":"MONTHLY COMB FLTR EFFLUENT (IESWTR/LT1)","ANALYTE_NAME":"IESWTR","RESULT":" ","RESULT_UOM":" ","MCL_VALUE":" ","MCL_UOM":" ","VIOL_BEGIN_DATE":"2016-04-01T07:00:00.000Z","VIOL_END_DATE":"2016-04-30T07:00:00.000Z","ENF_ACTION_NUMBER":"9501008","ENF_ACTION_ISSUE_DATE":"2018-02-28T08:00:00.000Z","ENF_ACTION_TYPE_ISSUED":"RETURN TO COMPLIANCE","WATER_SYSTEM_NAME":"REDCREST WATER WORKS","REGULATING_AGENCY":"DISTRICT 01 - KLAMATH","COUNTY":"HUMBOLDT","POPULATION":"100","CITY":"REDCREST","ZIPCODE":"95569"}]