[{"REGULATING_AGENCY":"DISTRICT 22 - ANGELES","WATER_SYSTEM_NUMBER":"CA1910249","WATER_SYSTEM_NAME":"WHITE FENCE FARMS MWC NO. 1","CLASSIFICATION":"COMMUNITY","POPULATION":1145,"SERVICE_CONNECTIONS":454,"COUNTY":"LOS ANGELES","CITY":"GLENDALE","ZIPCODE":91203,"VIOLATION_NUMBER":1022031,"VIOLATION_TYPE_NAME":"MCL,  AVERAGE","ANALYTE_NAME":"ARSENIC","RESULT":"0.0127 MG/L","MCL":" ","VIOL_BEGIN_DATE":"2019-04-01T07:00:00.000Z","VIOL_END_DATE":"2019-06-30T07:00:00.000Z","ENF_ACTION_NUMBER":9907014,"ENF_ACTION_ISSUE_DATE":"2019-08-13T07:00:00.000Z","ENF_ACTION_TYPE_ISSUED":"FORMAL ENFORCEMENT ACTION ISSUED"},{"REGULATING_AGENCY":"DISTRICT 22 - ANGELES","WATER_SYSTEM_NUMBER":"CA1910249","WATER_SYSTEM_NAME":"WHITE FENCE FARMS MWC NO. 1","CLASSIFICATION":"COMMUNITY","POPULATION":1145,"SERVICE_CONNECTIONS":454,"COUNTY":"LOS ANGELES","CITY":"GLENDALE","ZIPCODE":91203,"VIOLATION_NUMBER":1022032,"VIOLATION_TYPE_NAME":"MCL,  AVERAGE","ANALYTE_NAME":"ARSENIC","RESULT":"0.0127 MG/L","MCL":" ","VIOL_BEGIN_DATE":"2019-07-01T07:00:00.000Z","VIOL_END_DATE":"2019-09-30T07:00:00.000Z","ENF_ACTION_NUMBER":9907014,"ENF_ACTION_ISSUE_DATE":"2019-08-13T07:00:00.000Z","ENF_ACTION_TYPE_ISSUED":"FORMAL ENFORCEMENT ACTION ISSUED"}]