[{"WATER_SYSTEM_NUMBER":"CA2410018","VIOLATION_NUMBER":"9611002","VIOLATION_TYPE_NAME":"MCL,  AVERAGE","ANALYTE_NAME":"TTHM","RESULT":"0.082","RESULT_UOM":"MG/L","MCL_VALUE":"0.080","MCL_UOM":"MG/L","VIOL_BEGIN_DATE":"2014-07-01T07:00:00.000Z","VIOL_END_DATE":"2014-09-30T07:00:00.000Z","ENF_ACTION_NUMBER":"9311004","ENF_ACTION_ISSUE_DATE":"2014-12-30T08:00:00.000Z","ENF_ACTION_TYPE_ISSUED":"FORMAL ENFORCEMENT ACTION ISSUED","WATER_SYSTEM_NAME":"SANTA NELLA COUNTY WATER DISTRICT","REGULATING_AGENCY":"DISTRICT 11 - MERCED","COUNTY":"MERCED","POPULATION":"1308","CITY":"SANTA NELLA","ZIPCODE":"95322"},{"WATER_SYSTEM_NUMBER":"CA2410018","VIOLATION_NUMBER":"9611002","VIOLATION_TYPE_NAME":"MCL,  AVERAGE","ANALYTE_NAME":"TTHM","RESULT":"0.082","RESULT_UOM":"MG/L","MCL_VALUE":"0.080","MCL_UOM":"MG/L","VIOL_BEGIN_DATE":"2014-07-01T07:00:00.000Z","VIOL_END_DATE":"2014-09-30T07:00:00.000Z","ENF_ACTION_NUMBER":"9311008","ENF_ACTION_ISSUE_DATE":"2018-03-01T08:00:00.000Z","ENF_ACTION_TYPE_ISSUED":"RETURN TO COMPLIANCE","WATER_SYSTEM_NAME":"SANTA NELLA COUNTY WATER DISTRICT","REGULATING_AGENCY":"DISTRICT 11 - MERCED","COUNTY":"MERCED","POPULATION":"1308","CITY":"SANTA NELLA","ZIPCODE":"95322"}]