[{"REGULATING_AGENCY":"DISTRICT 24 - TULARE","WATER_SYSTEM_NUMBER":"CA5400735","WATER_SYSTEM_NAME":"RODRIGUEZ LABOR CAMP","CLASSIFICATION":"COMMUNITY","POPULATION":"110","SERVICE_CONNECTIONS":"35","COUNTY":"TULARE","CITY":"DELANO","ZIPCODE":"93215","VIOLATION_NUMBER":1200036,"VIOLATION_TYPE_NAME":"MCL, SINGLE SAMPLE","ANALYTE_NAME":"NITRATE","RESULT":"126","RESULT_UOM":"MG/L","MCL_VALUE":"45","MCL_UOM":"MG/L","VIOL_BEGIN_DATE":"2012-01-01T08:00:00.000Z","VIOL_END_DATE":"2012-03-31T08:00:00.000Z","ENF_ACTION_NUMBER":1003375,"ENF_ACTION_ISSUE_DATE":"2010-04-27T08:00:00.000Z","ENF_ACTION_TYPE_ISSUED":"FORMAL ENFORCEMENT ACTION ISSUED"},{"REGULATING_AGENCY":"DISTRICT 24 - TULARE","WATER_SYSTEM_NUMBER":"CA5400735","WATER_SYSTEM_NAME":"RODRIGUEZ LABOR CAMP","CLASSIFICATION":"COMMUNITY","POPULATION":"110","SERVICE_CONNECTIONS":"35","COUNTY":"TULARE","CITY":"DELANO","ZIPCODE":"93215","VIOLATION_NUMBER":1200036,"VIOLATION_TYPE_NAME":"MCL, SINGLE SAMPLE","ANALYTE_NAME":"NITRATE","RESULT":"126","RESULT_UOM":"MG/L","MCL_VALUE":"45","MCL_UOM":"MG/L","VIOL_BEGIN_DATE":"2012-01-01T08:00:00.000Z","VIOL_END_DATE":"2012-03-31T08:00:00.000Z","ENF_ACTION_NUMBER":9800441,"ENF_ACTION_ISSUE_DATE":"2015-11-03T08:00:00.000Z","ENF_ACTION_TYPE_ISSUED":"FORMAL ENFORCEMENT ACTION ISSUED"},{"REGULATING_AGENCY":"DISTRICT 24 - TULARE","WATER_SYSTEM_NUMBER":"CA5400735","WATER_SYSTEM_NAME":"RODRIGUEZ LABOR CAMP","CLASSIFICATION":"COMMUNITY","POPULATION":"110","SERVICE_CONNECTIONS":"35","COUNTY":"TULARE","CITY":"DELANO","ZIPCODE":"93215","VIOLATION_NUMBER":1200039,"VIOLATION_TYPE_NAME":"MCL, SINGLE SAMPLE","ANALYTE_NAME":"NITRATE","RESULT":"126","RESULT_UOM":"MG/L","MCL_VALUE":"45","MCL_UOM":"MG/L","VIOL_BEGIN_DATE":"2012-04-01T08:00:00.000Z","VIOL_END_DATE":"2012-06-30T08:00:00.000Z","ENF_ACTION_NUMBER":9800441,"ENF_ACTION_ISSUE_DATE":"2015-11-03T08:00:00.000Z","ENF_ACTION_TYPE_ISSUED":"FORMAL ENFORCEMENT ACTION ISSUED"},{"REGULATING_AGENCY":"DISTRICT 24 - TULARE","WATER_SYSTEM_NUMBER":"CA5400735","WATER_SYSTEM_NAME":"RODRIGUEZ LABOR CAMP","CLASSIFICATION":"COMMUNITY","POPULATION":"110","SERVICE_CONNECTIONS":"35","COUNTY":"TULARE","CITY":"DELANO","ZIPCODE":"93215","VIOLATION_NUMBER":1200039,"VIOLATION_TYPE_NAME":"MCL, SINGLE SAMPLE","ANALYTE_NAME":"NITRATE","RESULT":"126","RESULT_UOM":"MG/L","MCL_VALUE":"45","MCL_UOM":"MG/L","VIOL_BEGIN_DATE":"2012-04-01T08:00:00.000Z","VIOL_END_DATE":"2012-06-30T08:00:00.000Z","ENF_ACTION_NUMBER":1003375,"ENF_ACTION_ISSUE_DATE":"2010-04-27T08:00:00.000Z","ENF_ACTION_TYPE_ISSUED":"FORMAL ENFORCEMENT ACTION ISSUED"},{"REGULATING_AGENCY":"DISTRICT 24 - TULARE","WATER_SYSTEM_NUMBER":"CA5400735","WATER_SYSTEM_NAME":"RODRIGUEZ LABOR CAMP","CLASSIFICATION":"COMMUNITY","POPULATION":"110","SERVICE_CONNECTIONS":"35","COUNTY":"TULARE","CITY":"DELANO","ZIPCODE":"93215","VIOLATION_NUMBER":1200040,"VIOLATION_TYPE_NAME":"MCL, SINGLE SAMPLE","ANALYTE_NAME":"NITRATE","RESULT":"150","RESULT_UOM":"MG/L","MCL_VALUE":"45","MCL_UOM":"MG/L","VIOL_BEGIN_DATE":"2012-07-01T08:00:00.000Z","VIOL_END_DATE":"2012-09-30T08:00:00.000Z","ENF_ACTION_NUMBER":9800441,"ENF_ACTION_ISSUE_DATE":"2015-11-03T08:00:00.000Z","ENF_ACTION_TYPE_ISSUED":"FORMAL ENFORCEMENT ACTION ISSUED"},{"REGULATING_AGENCY":"DISTRICT 24 - TULARE","WATER_SYSTEM_NUMBER":"CA5400735","WATER_SYSTEM_NAME":"RODRIGUEZ LABOR CAMP","CLASSIFICATION":"COMMUNITY","POPULATION":"110","SERVICE_CONNECTIONS":"35","COUNTY":"TULARE","CITY":"DELANO","ZIPCODE":"93215","VIOLATION_NUMBER":1200040,"VIOLATION_TYPE_NAME":"MCL, SINGLE SAMPLE","ANALYTE_NAME":"NITRATE","RESULT":"150","RESULT_UOM":"MG/L","MCL_VALUE":"45","MCL_UOM":"MG/L","VIOL_BEGIN_DATE":"2012-07-01T08:00:00.000Z","VIOL_END_DATE":"2012-09-30T08:00:00.000Z","ENF_ACTION_NUMBER":1003375,"ENF_ACTION_ISSUE_DATE":"2010-04-27T08:00:00.000Z","ENF_ACTION_TYPE_ISSUED":"FORMAL ENFORCEMENT ACTION ISSUED"},{"REGULATING_AGENCY":"DISTRICT 24 - TULARE","WATER_SYSTEM_NUMBER":"CA5400735","WATER_SYSTEM_NAME":"RODRIGUEZ LABOR CAMP","CLASSIFICATION":"COMMUNITY","POPULATION":"110","SERVICE_CONNECTIONS":"35","COUNTY":"TULARE","CITY":"DELANO","ZIPCODE":"93215","VIOLATION_NUMBER":1300041,"VIOLATION_TYPE_NAME":"MCL, SINGLE SAMPLE","ANALYTE_NAME":"NITRATE","RESULT":"150","RESULT_UOM":"MG/L","MCL_VALUE":"45","MCL_UOM":"MG/L","VIOL_BEGIN_DATE":"2012-10-01T08:00:00.000Z","VIOL_END_DATE":"2012-12-31T08:00:00.000Z","ENF_ACTION_NUMBER":9800441,"ENF_ACTION_ISSUE_DATE":"2015-11-03T08:00:00.000Z","ENF_ACTION_TYPE_ISSUED":"FORMAL ENFORCEMENT ACTION ISSUED"},{"REGULATING_AGENCY":"DISTRICT 24 - TULARE","WATER_SYSTEM_NUMBER":"CA5400735","WATER_SYSTEM_NAME":"RODRIGUEZ LABOR CAMP","CLASSIFICATION":"COMMUNITY","POPULATION":"110","SERVICE_CONNECTIONS":"35","COUNTY":"TULARE","CITY":"DELANO","ZIPCODE":"93215","VIOLATION_NUMBER":1300041,"VIOLATION_TYPE_NAME":"MCL, SINGLE SAMPLE","ANALYTE_NAME":"NITRATE","RESULT":"150","RESULT_UOM":"MG/L","MCL_VALUE":"45","MCL_UOM":"MG/L","VIOL_BEGIN_DATE":"2012-10-01T08:00:00.000Z","VIOL_END_DATE":"2012-12-31T08:00:00.000Z","ENF_ACTION_NUMBER":1003375,"ENF_ACTION_ISSUE_DATE":"2010-04-27T08:00:00.000Z","ENF_ACTION_TYPE_ISSUED":"FORMAL ENFORCEMENT ACTION ISSUED"},{"REGULATING_AGENCY":"DISTRICT 24 - TULARE","WATER_SYSTEM_NUMBER":"CA5400735","WATER_SYSTEM_NAME":"RODRIGUEZ LABOR CAMP","CLASSIFICATION":"COMMUNITY","POPULATION":"110","SERVICE_CONNECTIONS":"35","COUNTY":"TULARE","CITY":"DELANO","ZIPCODE":"93215","VIOLATION_NUMBER":1300042,"VIOLATION_TYPE_NAME":"MCL, SINGLE SAMPLE","ANALYTE_NAME":"NITRATE","RESULT":"150","RESULT_UOM":"MG/L","MCL_VALUE":"45","MCL_UOM":"MG/L","VIOL_BEGIN_DATE":"2013-01-01T08:00:00.000Z","VIOL_END_DATE":"2013-03-31T08:00:00.000Z","ENF_ACTION_NUMBER":9800441,"ENF_ACTION_ISSUE_DATE":"2015-11-03T08:00:00.000Z","ENF_ACTION_TYPE_ISSUED":"FORMAL ENFORCEMENT ACTION ISSUED"},{"REGULATING_AGENCY":"DISTRICT 24 - TULARE","WATER_SYSTEM_NUMBER":"CA5400735","WATER_SYSTEM_NAME":"RODRIGUEZ LABOR CAMP","CLASSIFICATION":"COMMUNITY","POPULATION":"110","SERVICE_CONNECTIONS":"35","COUNTY":"TULARE","CITY":"DELANO","ZIPCODE":"93215","VIOLATION_NUMBER":1300042,"VIOLATION_TYPE_NAME":"MCL, SINGLE SAMPLE","ANALYTE_NAME":"NITRATE","RESULT":"150","RESULT_UOM":"MG/L","MCL_VALUE":"45","MCL_UOM":"MG/L","VIOL_BEGIN_DATE":"2013-01-01T08:00:00.000Z","VIOL_END_DATE":"2013-03-31T08:00:00.000Z","ENF_ACTION_NUMBER":1003375,"ENF_ACTION_ISSUE_DATE":"2010-04-27T08:00:00.000Z","ENF_ACTION_TYPE_ISSUED":"FORMAL ENFORCEMENT ACTION ISSUED"},{"REGULATING_AGENCY":"DISTRICT 24 - TULARE","WATER_SYSTEM_NUMBER":"CA5400735","WATER_SYSTEM_NAME":"RODRIGUEZ LABOR CAMP","CLASSIFICATION":"COMMUNITY","POPULATION":"110","SERVICE_CONNECTIONS":"35","COUNTY":"TULARE","CITY":"DELANO","ZIPCODE":"93215","VIOLATION_NUMBER":1300043,"VIOLATION_TYPE_NAME":"MCL, SINGLE SAMPLE","ANALYTE_NAME":"NITRATE","RESULT":"150","RESULT_UOM":"MG/L","MCL_VALUE":"45","MCL_UOM":"MG/L","VIOL_BEGIN_DATE":"2013-04-01T08:00:00.000Z","VIOL_END_DATE":"2013-06-30T08:00:00.000Z","ENF_ACTION_NUMBER":1003375,"ENF_ACTION_ISSUE_DATE":"2010-04-27T08:00:00.000Z","ENF_ACTION_TYPE_ISSUED":"FORMAL ENFORCEMENT ACTION ISSUED"},{"REGULATING_AGENCY":"DISTRICT 24 - TULARE","WATER_SYSTEM_NUMBER":"CA5400735","WATER_SYSTEM_NAME":"RODRIGUEZ LABOR CAMP","CLASSIFICATION":"COMMUNITY","POPULATION":"110","SERVICE_CONNECTIONS":"35","COUNTY":"TULARE","CITY":"DELANO","ZIPCODE":"93215","VIOLATION_NUMBER":1300043,"VIOLATION_TYPE_NAME":"MCL, SINGLE SAMPLE","ANALYTE_NAME":"NITRATE","RESULT":"150","RESULT_UOM":"MG/L","MCL_VALUE":"45","MCL_UOM":"MG/L","VIOL_BEGIN_DATE":"2013-04-01T08:00:00.000Z","VIOL_END_DATE":"2013-06-30T08:00:00.000Z","ENF_ACTION_NUMBER":9800441,"ENF_ACTION_ISSUE_DATE":"2015-11-03T08:00:00.000Z","ENF_ACTION_TYPE_ISSUED":"FORMAL ENFORCEMENT ACTION ISSUED"},{"REGULATING_AGENCY":"DISTRICT 24 - TULARE","WATER_SYSTEM_NUMBER":"CA5400735","WATER_SYSTEM_NAME":"RODRIGUEZ LABOR CAMP","CLASSIFICATION":"COMMUNITY","POPULATION":"110","SERVICE_CONNECTIONS":"35","COUNTY":"TULARE","CITY":"DELANO","ZIPCODE":"93215","VIOLATION_NUMBER":1300044,"VIOLATION_TYPE_NAME":"MCL, SINGLE SAMPLE","ANALYTE_NAME":"NITRATE","RESULT":"150","RESULT_UOM":"MG/L","MCL_VALUE":"45","MCL_UOM":"MG/L","VIOL_BEGIN_DATE":"2013-07-01T08:00:00.000Z","VIOL_END_DATE":"2013-09-30T08:00:00.000Z","ENF_ACTION_NUMBER":9800441,"ENF_ACTION_ISSUE_DATE":"2015-11-03T08:00:00.000Z","ENF_ACTION_TYPE_ISSUED":"FORMAL ENFORCEMENT ACTION ISSUED"},{"REGULATING_AGENCY":"DISTRICT 24 - TULARE","WATER_SYSTEM_NUMBER":"CA5400735","WATER_SYSTEM_NAME":"RODRIGUEZ LABOR CAMP","CLASSIFICATION":"COMMUNITY","POPULATION":"110","SERVICE_CONNECTIONS":"35","COUNTY":"TULARE","CITY":"DELANO","ZIPCODE":"93215","VIOLATION_NUMBER":1300044,"VIOLATION_TYPE_NAME":"MCL, SINGLE SAMPLE","ANALYTE_NAME":"NITRATE","RESULT":"150","RESULT_UOM":"MG/L","MCL_VALUE":"45","MCL_UOM":"MG/L","VIOL_BEGIN_DATE":"2013-07-01T08:00:00.000Z","VIOL_END_DATE":"2013-09-30T08:00:00.000Z","ENF_ACTION_NUMBER":1003375,"ENF_ACTION_ISSUE_DATE":"2010-04-27T08:00:00.000Z","ENF_ACTION_TYPE_ISSUED":"FORMAL ENFORCEMENT ACTION ISSUED"},{"REGULATING_AGENCY":"DISTRICT 24 - TULARE","WATER_SYSTEM_NUMBER":"CA5400735","WATER_SYSTEM_NAME":"RODRIGUEZ LABOR CAMP","CLASSIFICATION":"COMMUNITY","POPULATION":"110","SERVICE_CONNECTIONS":"35","COUNTY":"TULARE","CITY":"DELANO","ZIPCODE":"93215","VIOLATION_NUMBER":1400045,"VIOLATION_TYPE_NAME":"MCL, SINGLE SAMPLE","ANALYTE_NAME":"NITRATE","RESULT":"120","RESULT_UOM":"MG/L","MCL_VALUE":"45","MCL_UOM":"MG/L","VIOL_BEGIN_DATE":"2013-10-01T08:00:00.000Z","VIOL_END_DATE":"2013-12-31T08:00:00.000Z","ENF_ACTION_NUMBER":1003375,"ENF_ACTION_ISSUE_DATE":"2010-04-27T08:00:00.000Z","ENF_ACTION_TYPE_ISSUED":"FORMAL ENFORCEMENT ACTION ISSUED"},{"REGULATING_AGENCY":"DISTRICT 24 - TULARE","WATER_SYSTEM_NUMBER":"CA5400735","WATER_SYSTEM_NAME":"RODRIGUEZ LABOR CAMP","CLASSIFICATION":"COMMUNITY","POPULATION":"110","SERVICE_CONNECTIONS":"35","COUNTY":"TULARE","CITY":"DELANO","ZIPCODE":"93215","VIOLATION_NUMBER":1400045,"VIOLATION_TYPE_NAME":"MCL, SINGLE SAMPLE","ANALYTE_NAME":"NITRATE","RESULT":"120","RESULT_UOM":"MG/L","MCL_VALUE":"45","MCL_UOM":"MG/L","VIOL_BEGIN_DATE":"2013-10-01T08:00:00.000Z","VIOL_END_DATE":"2013-12-31T08:00:00.000Z","ENF_ACTION_NUMBER":9800441,"ENF_ACTION_ISSUE_DATE":"2015-11-03T08:00:00.000Z","ENF_ACTION_TYPE_ISSUED":"FORMAL ENFORCEMENT ACTION ISSUED"},{"REGULATING_AGENCY":"DISTRICT 24 - TULARE","WATER_SYSTEM_NUMBER":"CA5400735","WATER_SYSTEM_NAME":"RODRIGUEZ LABOR CAMP","CLASSIFICATION":"COMMUNITY","POPULATION":"110","SERVICE_CONNECTIONS":"35","COUNTY":"TULARE","CITY":"DELANO","ZIPCODE":"93215","VIOLATION_NUMBER":1400046,"VIOLATION_TYPE_NAME":"MCL, SINGLE SAMPLE","ANALYTE_NAME":"NITRATE","RESULT":"120","RESULT_UOM":"MG/L","MCL_VALUE":"45","MCL_UOM":"MG/L","VIOL_BEGIN_DATE":"2014-01-01T08:00:00.000Z","VIOL_END_DATE":"2014-03-31T08:00:00.000Z","ENF_ACTION_NUMBER":1003375,"ENF_ACTION_ISSUE_DATE":"2010-04-27T08:00:00.000Z","ENF_ACTION_TYPE_ISSUED":"FORMAL ENFORCEMENT ACTION ISSUED"},{"REGULATING_AGENCY":"DISTRICT 24 - TULARE","WATER_SYSTEM_NUMBER":"CA5400735","WATER_SYSTEM_NAME":"RODRIGUEZ LABOR CAMP","CLASSIFICATION":"COMMUNITY","POPULATION":"110","SERVICE_CONNECTIONS":"35","COUNTY":"TULARE","CITY":"DELANO","ZIPCODE":"93215","VIOLATION_NUMBER":1400046,"VIOLATION_TYPE_NAME":"MCL, SINGLE SAMPLE","ANALYTE_NAME":"NITRATE","RESULT":"120","RESULT_UOM":"MG/L","MCL_VALUE":"45","MCL_UOM":"MG/L","VIOL_BEGIN_DATE":"2014-01-01T08:00:00.000Z","VIOL_END_DATE":"2014-03-31T08:00:00.000Z","ENF_ACTION_NUMBER":9800441,"ENF_ACTION_ISSUE_DATE":"2015-11-03T08:00:00.000Z","ENF_ACTION_TYPE_ISSUED":"FORMAL ENFORCEMENT ACTION ISSUED"},{"REGULATING_AGENCY":"DISTRICT 24 - TULARE","WATER_SYSTEM_NUMBER":"CA5400735","WATER_SYSTEM_NAME":"RODRIGUEZ LABOR CAMP","CLASSIFICATION":"COMMUNITY","POPULATION":"110","SERVICE_CONNECTIONS":"35","COUNTY":"TULARE","CITY":"DELANO","ZIPCODE":"93215","VIOLATION_NUMBER":1400050,"VIOLATION_TYPE_NAME":"MCL, SINGLE SAMPLE","ANALYTE_NAME":"NITRATE","RESULT":"138","RESULT_UOM":"MG/L","MCL_VALUE":"45","MCL_UOM":"MG/L","VIOL_BEGIN_DATE":"2015-07-01T08:00:00.000Z","VIOL_END_DATE":"2015-09-30T08:00:00.000Z","ENF_ACTION_NUMBER":9800441,"ENF_ACTION_ISSUE_DATE":"2015-11-03T08:00:00.000Z","ENF_ACTION_TYPE_ISSUED":"FORMAL ENFORCEMENT ACTION ISSUED"},{"REGULATING_AGENCY":"DISTRICT 24 - TULARE","WATER_SYSTEM_NUMBER":"CA5400735","WATER_SYSTEM_NAME":"RODRIGUEZ LABOR CAMP","CLASSIFICATION":"COMMUNITY","POPULATION":"110","SERVICE_CONNECTIONS":"35","COUNTY":"TULARE","CITY":"DELANO","ZIPCODE":"93215","VIOLATION_NUMBER":1400051,"VIOLATION_TYPE_NAME":"MCL, SINGLE SAMPLE","ANALYTE_NAME":"NITRATE","RESULT":"22.6","RESULT_UOM":"MG/L","MCL_VALUE":"10","MCL_UOM":"MG/L","VIOL_BEGIN_DATE":"2015-10-01T08:00:00.000Z","VIOL_END_DATE":"2015-12-31T08:00:00.000Z","ENF_ACTION_NUMBER":9800441,"ENF_ACTION_ISSUE_DATE":"2015-11-03T08:00:00.000Z","ENF_ACTION_TYPE_ISSUED":"FORMAL ENFORCEMENT ACTION ISSUED"},{"REGULATING_AGENCY":"DISTRICT 24 - TULARE","WATER_SYSTEM_NUMBER":"CA5400735","WATER_SYSTEM_NAME":"RODRIGUEZ LABOR CAMP","CLASSIFICATION":"COMMUNITY","POPULATION":"110","SERVICE_CONNECTIONS":"35","COUNTY":"TULARE","CITY":"DELANO","ZIPCODE":"93215","VIOLATION_NUMBER":1400052,"VIOLATION_TYPE_NAME":"MCL, SINGLE SAMPLE","ANALYTE_NAME":"NITRATE","RESULT":"21.7","RESULT_UOM":"MG/L","MCL_VALUE":"10","MCL_UOM":"MG/L","VIOL_BEGIN_DATE":"2016-01-01T08:00:00.000Z","VIOL_END_DATE":"2016-03-31T08:00:00.000Z","ENF_ACTION_NUMBER":9800441,"ENF_ACTION_ISSUE_DATE":"2015-11-03T08:00:00.000Z","ENF_ACTION_TYPE_ISSUED":"FORMAL ENFORCEMENT ACTION ISSUED"},{"REGULATING_AGENCY":"DISTRICT 24 - TULARE","WATER_SYSTEM_NUMBER":"CA5400735","WATER_SYSTEM_NAME":"RODRIGUEZ LABOR CAMP","CLASSIFICATION":"COMMUNITY","POPULATION":"110","SERVICE_CONNECTIONS":"35","COUNTY":"TULARE","CITY":"DELANO","ZIPCODE":"93215","VIOLATION_NUMBER":1400053,"VIOLATION_TYPE_NAME":"MCL, SINGLE SAMPLE","ANALYTE_NAME":"NITRATE","RESULT":"24.4","RESULT_UOM":"MG/L","MCL_VALUE":"10","MCL_UOM":"MG/L","VIOL_BEGIN_DATE":"2016-04-01T08:00:00.000Z","VIOL_END_DATE":"2016-06-30T08:00:00.000Z","ENF_ACTION_NUMBER":9800441,"ENF_ACTION_ISSUE_DATE":"2015-11-03T08:00:00.000Z","ENF_ACTION_TYPE_ISSUED":"FORMAL ENFORCEMENT ACTION ISSUED"},{"REGULATING_AGENCY":"DISTRICT 24 - TULARE","WATER_SYSTEM_NUMBER":"CA5400735","WATER_SYSTEM_NAME":"RODRIGUEZ LABOR CAMP","CLASSIFICATION":"COMMUNITY","POPULATION":"110","SERVICE_CONNECTIONS":"35","COUNTY":"TULARE","CITY":"DELANO","ZIPCODE":"93215","VIOLATION_NUMBER":1400054,"VIOLATION_TYPE_NAME":"MCL, SINGLE SAMPLE","ANALYTE_NAME":"NITRATE","RESULT":"26.9","RESULT_UOM":"MG/L","MCL_VALUE":"10","MCL_UOM":"MG/L","VIOL_BEGIN_DATE":"2016-07-01T08:00:00.000Z","VIOL_END_DATE":"2016-09-30T08:00:00.000Z","ENF_ACTION_NUMBER":9800441,"ENF_ACTION_ISSUE_DATE":"2015-11-03T08:00:00.000Z","ENF_ACTION_TYPE_ISSUED":"FORMAL ENFORCEMENT ACTION ISSUED"},{"REGULATING_AGENCY":"DISTRICT 24 - TULARE","WATER_SYSTEM_NUMBER":"CA5400735","WATER_SYSTEM_NAME":"RODRIGUEZ LABOR CAMP","CLASSIFICATION":"COMMUNITY","POPULATION":"110","SERVICE_CONNECTIONS":"35","COUNTY":"TULARE","CITY":"DELANO","ZIPCODE":"93215","VIOLATION_NUMBER":1400055,"VIOLATION_TYPE_NAME":"MCL, SINGLE SAMPLE","ANALYTE_NAME":"NITRATE","RESULT":"27.8","RESULT_UOM":"MG/L","MCL_VALUE":"10","MCL_UOM":"MG/L","VIOL_BEGIN_DATE":"2016-10-01T08:00:00.000Z","VIOL_END_DATE":"2016-12-31T08:00:00.000Z","ENF_ACTION_NUMBER":9800441,"ENF_ACTION_ISSUE_DATE":"2015-11-03T08:00:00.000Z","ENF_ACTION_TYPE_ISSUED":"FORMAL ENFORCEMENT ACTION ISSUED"},{"REGULATING_AGENCY":"DISTRICT 24 - TULARE","WATER_SYSTEM_NUMBER":"CA5400735","WATER_SYSTEM_NAME":"RODRIGUEZ LABOR CAMP","CLASSIFICATION":"COMMUNITY","POPULATION":"110","SERVICE_CONNECTIONS":"35","COUNTY":"TULARE","CITY":"DELANO","ZIPCODE":"93215","VIOLATION_NUMBER":1400057,"VIOLATION_TYPE_NAME":"MCL, SINGLE SAMPLE","ANALYTE_NAME":"NITRATE","RESULT":"22.4","RESULT_UOM":"MG/L","MCL_VALUE":"10","MCL_UOM":"MG/L","VIOL_BEGIN_DATE":"2017-01-01T08:00:00.000Z","VIOL_END_DATE":"2017-03-31T08:00:00.000Z","ENF_ACTION_NUMBER":9800441,"ENF_ACTION_ISSUE_DATE":"2015-11-03T08:00:00.000Z","ENF_ACTION_TYPE_ISSUED":"FORMAL ENFORCEMENT ACTION ISSUED"},{"REGULATING_AGENCY":"DISTRICT 24 - TULARE","WATER_SYSTEM_NUMBER":"CA5400735","WATER_SYSTEM_NAME":"RODRIGUEZ LABOR CAMP","CLASSIFICATION":"COMMUNITY","POPULATION":"110","SERVICE_CONNECTIONS":"35","COUNTY":"TULARE","CITY":"DELANO","ZIPCODE":"93215","VIOLATION_NUMBER":1400058,"VIOLATION_TYPE_NAME":"MCL, SINGLE SAMPLE","ANALYTE_NAME":"NITRATE","RESULT":"26.4","RESULT_UOM":"MG/L","MCL_VALUE":"10","MCL_UOM":"MG/L","VIOL_BEGIN_DATE":"2017-04-01T08:00:00.000Z","VIOL_END_DATE":"2017-06-30T08:00:00.000Z","ENF_ACTION_NUMBER":9800441,"ENF_ACTION_ISSUE_DATE":"2015-11-03T08:00:00.000Z","ENF_ACTION_TYPE_ISSUED":"FORMAL ENFORCEMENT ACTION ISSUED"},{"REGULATING_AGENCY":"DISTRICT 24 - TULARE","WATER_SYSTEM_NUMBER":"CA5400735","WATER_SYSTEM_NAME":"RODRIGUEZ LABOR CAMP","CLASSIFICATION":"COMMUNITY","POPULATION":"110","SERVICE_CONNECTIONS":"35","COUNTY":"TULARE","CITY":"DELANO","ZIPCODE":"93215","VIOLATION_NUMBER":1400059,"VIOLATION_TYPE_NAME":"MCL, SINGLE SAMPLE","ANALYTE_NAME":"NITRATE","RESULT":"27.2","RESULT_UOM":"MG/L","MCL_VALUE":"10","MCL_UOM":"MG/L","VIOL_BEGIN_DATE":"2017-07-01T08:00:00.000Z","VIOL_END_DATE":"2017-09-30T08:00:00.000Z","ENF_ACTION_NUMBER":9800441,"ENF_ACTION_ISSUE_DATE":"2015-11-03T08:00:00.000Z","ENF_ACTION_TYPE_ISSUED":"FORMAL ENFORCEMENT ACTION ISSUED"},{"REGULATING_AGENCY":"DISTRICT 24 - TULARE","WATER_SYSTEM_NUMBER":"CA5400735","WATER_SYSTEM_NAME":"RODRIGUEZ LABOR CAMP","CLASSIFICATION":"COMMUNITY","POPULATION":"110","SERVICE_CONNECTIONS":"35","COUNTY":"TULARE","CITY":"DELANO","ZIPCODE":"93215","VIOLATION_NUMBER":1400060,"VIOLATION_TYPE_NAME":"MCL, SINGLE SAMPLE","ANALYTE_NAME":"NITRATE","RESULT":"22.9","RESULT_UOM":"MG/L","MCL_VALUE":"10","MCL_UOM":"MG/L","VIOL_BEGIN_DATE":"2017-10-01T08:00:00.000Z","VIOL_END_DATE":"2017-12-31T08:00:00.000Z","ENF_ACTION_NUMBER":9800441,"ENF_ACTION_ISSUE_DATE":"2015-11-03T08:00:00.000Z","ENF_ACTION_TYPE_ISSUED":"FORMAL ENFORCEMENT ACTION ISSUED"},{"REGULATING_AGENCY":"DISTRICT 24 - TULARE","WATER_SYSTEM_NUMBER":"CA5400735","WATER_SYSTEM_NAME":"RODRIGUEZ LABOR CAMP","CLASSIFICATION":"COMMUNITY","POPULATION":"110","SERVICE_CONNECTIONS":"35","COUNTY":"TULARE","CITY":"DELANO","ZIPCODE":"93215","VIOLATION_NUMBER":1400062,"VIOLATION_TYPE_NAME":"MCL, SINGLE SAMPLE","ANALYTE_NAME":"NITRATE","RESULT":"23.4","RESULT_UOM":"MG/L","MCL_VALUE":"10","MCL_UOM":"MG/L","VIOL_BEGIN_DATE":"2018-01-01T08:00:00.000Z","VIOL_END_DATE":"2018-03-31T08:00:00.000Z","ENF_ACTION_NUMBER":9800441,"ENF_ACTION_ISSUE_DATE":"2015-11-03T08:00:00.000Z","ENF_ACTION_TYPE_ISSUED":"FORMAL ENFORCEMENT ACTION ISSUED"},{"REGULATING_AGENCY":"DISTRICT 24 - TULARE","WATER_SYSTEM_NUMBER":"CA5400735","WATER_SYSTEM_NAME":"RODRIGUEZ LABOR CAMP","CLASSIFICATION":"COMMUNITY","POPULATION":"110","SERVICE_CONNECTIONS":"35","COUNTY":"TULARE","CITY":"DELANO","ZIPCODE":"93215","VIOLATION_NUMBER":1400063,"VIOLATION_TYPE_NAME":"MCL, SINGLE SAMPLE","ANALYTE_NAME":"NITRATE","RESULT":"26.3","RESULT_UOM":"MG/L","MCL_VALUE":"10","MCL_UOM":"MG/L","VIOL_BEGIN_DATE":"2018-04-01T08:00:00.000Z","VIOL_END_DATE":"2018-06-30T08:00:00.000Z","ENF_ACTION_NUMBER":9800441,"ENF_ACTION_ISSUE_DATE":"2015-11-03T08:00:00.000Z","ENF_ACTION_TYPE_ISSUED":"FORMAL ENFORCEMENT ACTION ISSUED"},{"REGULATING_AGENCY":"DISTRICT 24 - TULARE","WATER_SYSTEM_NUMBER":"CA5400735","WATER_SYSTEM_NAME":"RODRIGUEZ LABOR CAMP","CLASSIFICATION":"COMMUNITY","POPULATION":"110","SERVICE_CONNECTIONS":"35","COUNTY":"TULARE","CITY":"DELANO","ZIPCODE":"93215","VIOLATION_NUMBER":1400064,"VIOLATION_TYPE_NAME":"MCL, SINGLE SAMPLE","ANALYTE_NAME":"NITRATE","RESULT":"25.5","RESULT_UOM":"MG/L","MCL_VALUE":"10","MCL_UOM":"MG/L","VIOL_BEGIN_DATE":"2018-07-01T08:00:00.000Z","VIOL_END_DATE":"2018-09-30T08:00:00.000Z","ENF_ACTION_NUMBER":9800441,"ENF_ACTION_ISSUE_DATE":"2015-11-03T08:00:00.000Z","ENF_ACTION_TYPE_ISSUED":"FORMAL ENFORCEMENT ACTION ISSUED"},{"REGULATING_AGENCY":"DISTRICT 24 - TULARE","WATER_SYSTEM_NUMBER":"CA5400735","WATER_SYSTEM_NAME":"RODRIGUEZ LABOR CAMP","CLASSIFICATION":"COMMUNITY","POPULATION":"110","SERVICE_CONNECTIONS":"35","COUNTY":"TULARE","CITY":"DELANO","ZIPCODE":"93215","VIOLATION_NUMBER":1400065,"VIOLATION_TYPE_NAME":"STATE PRIMARY MCL VIOL - NOT CR6","ANALYTE_NAME":"1,2,3-TRICHLOROPROPANE","RESULT":"0.008","RESULT_UOM":"UG/L","MCL_VALUE":"0.005","MCL_UOM":"UG/L","VIOL_BEGIN_DATE":"2018-10-01T08:00:00.000Z","VIOL_END_DATE":"2018-12-31T08:00:00.000Z","ENF_ACTION_NUMBER":9800444,"ENF_ACTION_ISSUE_DATE":"2018-12-21T08:00:00.000Z","ENF_ACTION_TYPE_ISSUED":"CA STATE ACTION ISSUED"},{"REGULATING_AGENCY":"DISTRICT 24 - TULARE","WATER_SYSTEM_NUMBER":"CA5400735","WATER_SYSTEM_NAME":"RODRIGUEZ LABOR CAMP","CLASSIFICATION":"COMMUNITY","POPULATION":"110","SERVICE_CONNECTIONS":"35","COUNTY":"TULARE","CITY":"DELANO","ZIPCODE":"93215","VIOLATION_NUMBER":1400066,"VIOLATION_TYPE_NAME":"MCL, SINGLE SAMPLE","ANALYTE_NAME":"NITRATE","RESULT":"23","RESULT_UOM":"MG/L","MCL_VALUE":"10","MCL_UOM":"MG/L","VIOL_BEGIN_DATE":"2018-10-01T08:00:00.000Z","VIOL_END_DATE":"2018-12-31T08:00:00.000Z","ENF_ACTION_NUMBER":9800441,"ENF_ACTION_ISSUE_DATE":"2015-11-03T08:00:00.000Z","ENF_ACTION_TYPE_ISSUED":"FORMAL ENFORCEMENT ACTION ISSUED"},{"REGULATING_AGENCY":"DISTRICT 24 - TULARE","WATER_SYSTEM_NUMBER":"CA5400735","WATER_SYSTEM_NAME":"RODRIGUEZ LABOR CAMP","CLASSIFICATION":"COMMUNITY","POPULATION":"110","SERVICE_CONNECTIONS":"35","COUNTY":"TULARE","CITY":"DELANO","ZIPCODE":"93215","VIOLATION_NUMBER":1400067,"VIOLATION_TYPE_NAME":"MCL, SINGLE SAMPLE","ANALYTE_NAME":"NITRATE","RESULT":"21","RESULT_UOM":"MG/L","MCL_VALUE":"10","MCL_UOM":"MG/L","VIOL_BEGIN_DATE":"2019-01-01T08:00:00.000Z","VIOL_END_DATE":"2019-03-31T08:00:00.000Z","ENF_ACTION_NUMBER":9800441,"ENF_ACTION_ISSUE_DATE":"2015-11-03T08:00:00.000Z","ENF_ACTION_TYPE_ISSUED":"FORMAL ENFORCEMENT ACTION ISSUED"},{"REGULATING_AGENCY":"DISTRICT 24 - TULARE","WATER_SYSTEM_NUMBER":"CA5400735","WATER_SYSTEM_NAME":"RODRIGUEZ LABOR CAMP","CLASSIFICATION":"COMMUNITY","POPULATION":"110","SERVICE_CONNECTIONS":"35","COUNTY":"TULARE","CITY":"DELANO","ZIPCODE":"93215","VIOLATION_NUMBER":1400068,"VIOLATION_TYPE_NAME":"STATE PRIMARY MCL VIOL - NOT CR6","ANALYTE_NAME":"1,2,3-TRICHLOROPROPANE","RESULT":"0.0075","RESULT_UOM":"UG/L","MCL_VALUE":"0.005","MCL_UOM":"UG/L","VIOL_BEGIN_DATE":"2019-01-01T08:00:00.000Z","VIOL_END_DATE":"2019-03-31T08:00:00.000Z","ENF_ACTION_NUMBER":9800444,"ENF_ACTION_ISSUE_DATE":"2018-12-21T08:00:00.000Z","ENF_ACTION_TYPE_ISSUED":"CA STATE ACTION ISSUED"},{"REGULATING_AGENCY":"DISTRICT 24 - TULARE","WATER_SYSTEM_NUMBER":"CA5400735","WATER_SYSTEM_NAME":"RODRIGUEZ LABOR CAMP","CLASSIFICATION":"COMMUNITY","POPULATION":"110","SERVICE_CONNECTIONS":"35","COUNTY":"TULARE","CITY":"DELANO","ZIPCODE":"93215","VIOLATION_NUMBER":1400069,"VIOLATION_TYPE_NAME":"MCL, SINGLE SAMPLE","ANALYTE_NAME":"NITRATE","RESULT":"25.5","RESULT_UOM":"MG/L","MCL_VALUE":"10","MCL_UOM":"MG/L","VIOL_BEGIN_DATE":"2019-04-01T08:00:00.000Z","VIOL_END_DATE":"2019-06-30T08:00:00.000Z","ENF_ACTION_NUMBER":9800441,"ENF_ACTION_ISSUE_DATE":"2015-11-03T08:00:00.000Z","ENF_ACTION_TYPE_ISSUED":"FORMAL ENFORCEMENT ACTION ISSUED"},{"REGULATING_AGENCY":"DISTRICT 24 - TULARE","WATER_SYSTEM_NUMBER":"CA5400735","WATER_SYSTEM_NAME":"RODRIGUEZ LABOR CAMP","CLASSIFICATION":"COMMUNITY","POPULATION":"110","SERVICE_CONNECTIONS":"35","COUNTY":"TULARE","CITY":"DELANO","ZIPCODE":"93215","VIOLATION_NUMBER":1400070,"VIOLATION_TYPE_NAME":"STATE PRIMARY MCL VIOL - NOT CR6","ANALYTE_NAME":"1,2,3-TRICHLOROPROPANE","RESULT":"0.0078","RESULT_UOM":"UG/L","MCL_VALUE":"0.005","MCL_UOM":"UG/L","VIOL_BEGIN_DATE":"2019-04-01T08:00:00.000Z","VIOL_END_DATE":"2019-06-30T08:00:00.000Z","ENF_ACTION_NUMBER":9800444,"ENF_ACTION_ISSUE_DATE":"2018-12-21T08:00:00.000Z","ENF_ACTION_TYPE_ISSUED":"CA STATE ACTION ISSUED"}]