{"type":"Feature","properties":{"ObjectID":89244,"WATER_SYST":"CA3701934","WATER_SY_1":"PINE VALLEY BIBLE CONFERENCE CENTER","REGULATING":"LPA67 - SAN DIEGO COUNTY","COUNTY":"SAN DIEGO","POPULATION":"350","CLASSIFICA":"COMMUNITY","CITY_1":"PINE VALLEY","ZIPCODE":"91962","GIS_STATUS":"IN COMPLIANCE","DEFAULT_ME":"NO VIOLATION OF THE PRIMARY DRINKING WATER STANDARDS HAVE BEEN RECORDED SINCE 1/1/2012","Service_Co":44},"geometry":{"type":"Point","coordinates":[-116.38850806899968,32.70691990600045]}}