{"type":"Feature","properties":{"ObjectID":93514,"WATER_SYST":"CA1010019","WATER_SY_1":"KINGSBURG, CITY OF","REGULATING":"DISTRICT 23 - FRESNO","COUNTY":"FRESNO","POPULATION":"11504","CLASSIFICA":"COMMUNITY","CITY_1":"KINGSBURG","ZIPCODE":"93631","GIS_STATUS":"OUT-OF-COMPLIANCE","DEFAULT_ME":null,"Service_Co":3704,"DETAILED_V":"https://www.waterboards.ca.gov/water_issues/programs/hr2w/docs/data/hr2w_web_data_active.xlsx"},"geometry":{"type":"Point","coordinates":[-119.55348176910783,36.51619900468722]}}