{"type":"Feature","properties":{"ObjectID":87585,"WATER_SYST":"CA3310001","WATER_SY_1":"COACHELLA VWD: COVE COMMUNITY","REGULATING":"DISTRICT 20 - RIVERSIDE","COUNTY":"RIVERSIDE","POPULATION":"280000","CLASSIFICA":"COMMUNITY","CITY_1":"PALM DESERT","ZIPCODE":"92211","GIS_STATUS":"IN COMPLIANCE","DEFAULT_ME":"NO VIOLATION OF THE PRIMARY DRINKING WATER STANDARDS HAVE BEEN RECORDED SINCE 1/1/2012","Service_Co":104188},"geometry":{"type":"Point","coordinates":[-116.30929317899972,33.75203810200048]}}