{"type":"Feature","properties":{"ObjectID":96102,"WATER_SYST":"CA5400523","WATER_SY_1":"EL MONTE VILLAGE MHP","REGULATING":"DISTRICT 24 - TULARE","COUNTY":"TULARE","POPULATION":"100","CLASSIFICA":"COMMUNITY","CITY_1":"DINUBA","ZIPCODE":"93618","GIS_STATUS":"RETURNED TO COMPLIANCE","DEFAULT_ME":null,"Service_Co":47,"DETAILED_V":"https://www.waterboards.ca.gov/water_issues/programs/hr2w/docs/data/hr2w_web_data_rtc.xlsx"},"geometry":{"type":"Point","coordinates":[-119.38836296224824,36.5475331808856]}}